{"success":true,"data":{"subscription":{"id":"16BgXIUxqug513t51","billing_period":1,"billing_period_unit":"month","customer_id":"AzqVvyUxqvU883t1h","status":"active","current_term_start":1774479374,"current_term_end":1777157774,"next_billing_at":1777157774,"created_at":1758840974,"started_at":1758840974,"activated_at":1758840974,"created_from_ip":"174.244.32.105","updated_at":1774479383,"has_scheduled_changes":false,"channel":"web","resource_version":1774479383131,"deleted":false,"object":"subscription","currency_code":"USD","subscription_items":[{"item_price_id":"Nomad-Unlimited-Residential-Plan-USD-Monthly","item_type":"plan","quantity":1,"unit_price":9995,"amount":9995,"free_quantity":0,"object":"subscription_item"}],"shipping_address":{"email":"kdallen798@gmail.com","line1":"1870 Downsville Rd","city":"Downsville","state_code":"LA","state":"Louisiana","country":"US","zip":"71234","validation_status":"not_validated","object":"shipping_address"},"due_invoices_count":5,"due_since":1764114974,"total_dues":49975,"mrr":9995,"exchange_rate":1,"base_currency_code":"USD","cf_SIM_ID_ICCID":"89148000011736732569","cf_Device_IMEI":"357632331445246","has_scheduled_advance_invoices":false,"decommissioned":false},"transactions":[{"id":"txn_Azi8NJVEvGcWv4P4m","status":"failure","amount":9995},{"id":"txn_AzqUqcVCHn0f26vpv","status":"failure","amount":9995},{"id":"txn_AzqFXqVAroc5r6twj","status":"failure","amount":9995},{"id":"txn_AziKfyV9emR4B6oq","status":"failure","amount":9995},{"id":"txn_16BgQiV9elT8U62L","status":"failure","amount":9995}]}}